<?xml version="1.0" encoding="UTF-8"?>
<objects serializationModel="Studio.01.10.00">
    <object class="AudioFile" id="{823df2f4-31ec-49e1-9c1a-ac95c817bc0d}">
        <property name="assetPath">
            <value>Ignite 1.wav</value>
        </property>
        <property name="frequencyInKHz">
            <value>44.0999985</value>
        </property>
        <property name="channelCount">
            <value>2</value>
        </property>
        <property name="length">
            <value>2.25</value>
        </property>
        <relationship name="masterAssetFolder">
            <destination>{1791510b-0781-4201-b846-d25dfc8e3e10}</destination>
        </relationship>
    </object>
</objects>
